carloancalculator.py
mindpowered_carloancalculator/CarLoanCalculator.py
mindpowered_carloancalculator/__init__.py
mindpowered_carloancalculator-0.0.7.dist-info/LICENSE.txt
mindpowered_carloancalculator-0.0.7.dist-info/METADATA
mindpowered_carloancalculator-0.0.7.dist-info/WHEEL
mindpowered_carloancalculator-0.0.7.dist-info/top_level.txt
mindpowered_carloancalculator-0.0.7.dist-info/RECORD
