Metadata-Version: 2.1
Name: mindpowered-carloancalculator
Version: 0.0.7
Summary: Car Loan Auto Loan Payment Calculator - Calculate financing on a new car including trade-in and taxes
Home-page: https://mindpowered.dev/
Author: Mind Powered Corporation
Author-email: support@mindpowered.dev
License: MIT
Platform: UNKNOWN
Classifier: Programming Language :: Python :: 3
Classifier: Operating System :: OS Independent
Classifier: License :: OSI Approved :: MIT License
Requires-Dist: mindpowered-maglev
